README.md
setup.py
cifl_google_wrapper/__init__.py
cifl_google_wrapper.egg-info/PKG-INFO
cifl_google_wrapper.egg-info/SOURCES.txt
cifl_google_wrapper.egg-info/dependency_links.txt
cifl_google_wrapper.egg-info/not-zip-safe
cifl_google_wrapper.egg-info/requires.txt
cifl_google_wrapper.egg-info/top_level.txt
cifl_google_wrapper/api_adsense/__init__.py
cifl_google_wrapper/api_adwords/__init__.py
cifl_google_wrapper/api_big_query/__init__.py
cifl_google_wrapper/api_ga_mcf/__init__.py
cifl_google_wrapper/api_google_sheets/__init__.py
cifl_google_wrapper/api_search_console/__init__.py
cifl_google_wrapper/cifl_singer/__init__.py