Metadata-Version: 1.0
Name: cifl-google-wrapper
Version: 0.1.6
Summary: A wrapper for CIFL taps and targets
Home-page: https://github.com/coding-is-for-losers/singer-taps-and-targets-v1.1/tree/master/cifl_google_wrapper
Author: CIFL
Author-email: UNKNOWN
License: MIT
Platform: UNKNOWN
